cmsplugin_news3
