Metadata-Version: 1.1
Name: cmsplugin-news3
Version: 0.0.2
Summary: News plugin and application for Django-CMS 3.x
Home-page: https://github.com/vader666/cmsplugin_news3
Author: Anton Chertikovtzev
Author-email: anton.chertikovtcev@gmail.com
License: UNKNOWN
Platform: UNKNOWN
Classifier: Development Status :: 3 - Alpha
Classifier: Environment :: Web Environment
Classifier: Intended Audience :: Developers
Classifier: Operating System :: OS Independent
Classifier: Programming Language :: Python
Classifier: Framework :: Django
